{
  "version": "1.0.0",
  "setup_date": "2026-01-01T00:00:00Z",
  "setup_by": "team-member-name",
  "workspace_paths": {
    "sources": "/path/to/nansen/sources",
    "intelligence": "/path/to/nansen/intelligence",
    "outputs": "/path/to/nansen/outputs"
  },
  "google_drive": {
    "installed": false,
    "mount_path": null,
    "shared_drive_folder": null,
    "sync_configured": false
  },
  "fathom": {
    "connected": false,
    "api_key_set": false
  },
  "slack": {
    "mcp_connected": false
  },
  "sync": {
    "enabled": true,
    "last_full_sync": null,
    "last_slack_sync": {},
    "last_fathom_sync": null,
    "slack": {
      "channels": []
    },
    "fathom": {
      "min_duration_minutes": 5
    },
    "scheduled_task_id": null,
    "preferred_time": null
  },
  "pilot_group": true
}
